dys/__init__.py
dys/__main__.py
dys/bs.py
dys/domain.py
dys/fb.py
dys/metric.py
dys/neutralize.py
dys/stockutil.py
dys-0.2.9.dist-info/LICENSE
dys-0.2.9.dist-info/METADATA
dys-0.2.9.dist-info/WHEEL
dys-0.2.9.dist-info/entry_points.txt
dys-0.2.9.dist-info/top_level.txt
dys-0.2.9.dist-info/RECORD
