Metadata-Version: 2.1
Name: dys
Version: 0.2.9
Summary: Awesome dys created by ryanzhang
Home-page: https://github.com/ryanzhang/dys/
Author: ryanzhang
License: UNKNOWN
Platform: UNKNOWN
Requires-Dist: kupy
Requires-Dist: sklearn
